dhravyapy/__init__.py
dhravyapy/assets.py
dhravyapy/errors.py
dhravyapy/fun.py
dhravyapy/http.py
dhravyapy/image.py
dhravyapy/info.py
dhravyapy/misc.py
dhravyapy-0.0.9.dist-info/LICENSE
dhravyapy-0.0.9.dist-info/METADATA
dhravyapy-0.0.9.dist-info/WHEEL
dhravyapy-0.0.9.dist-info/top_level.txt
dhravyapy-0.0.9.dist-info/RECORD
