Metadata-Version: 2.1
Name: dhravyapy
Version: 0.0.9
Summary: An asynchronous wrapper for interacting with the Dhravya API
Home-page: https://github.com/27Saumya/dhravyapy
Download-URL: https://github.com/27Saumya/dhravyapy/archive/v0.0.9.tar.gz
Author: 27Saumya
License: MIT
Platform: UNKNOWN
Classifier: Development Status :: 4 - Beta
Classifier: Intended Audience :: Developers
Classifier: License :: OSI Approved :: MIT License
Classifier: Programming Language :: Python :: 3.8
Classifier: Topic :: Software Development :: Libraries :: Python Modules
Requires-Python: >=3.8.0
License-File: LICENSE
Requires-Dist: aiohttp (<3.9.0,>=3.6.0)
Requires-Dist: aiofiles
